pynndescent/__init__.py
pynndescent/distances.py
pynndescent/graph_utils.py
pynndescent/optimal_transport.py
pynndescent/pynndescent_.py
pynndescent/rp_trees.py
pynndescent/sparse.py
pynndescent/sparse_nndescent.py
pynndescent/threaded_rp_trees.py
pynndescent/utils.py
pynndescent-0.5.13.dist-info/LICENSE
pynndescent-0.5.13.dist-info/METADATA
pynndescent-0.5.13.dist-info/WHEEL
pynndescent-0.5.13.dist-info/top_level.txt
pynndescent-0.5.13.dist-info/RECORD
